<?xml version="1.0" encoding="utf-8"?>
<savedqueries xmlns:xsi="http://www.w3.org/2001/XMLSchema-instance">
  <savedquery>
    <IsCustomizable>1</IsCustomizable>
    <CanBeDeleted>0</CanBeDeleted>
    <isquickfindquery>0</isquickfindquery>
    <isprivate>0</isprivate>
    <isdefault>0</isdefault>
    <savedqueryid>{3da2964c-d510-438d-b31b-503047cd3a38}</savedqueryid>
    <layoutxml>
      <grid name="resultset" jump="ans_filename" select="1" icon="1" preview="1">
        <row name="result" id="ans_uploadid">
          <cell name="ans_filename" width="300" />
          <cell name="createdon" width="125" />
        </row>
      </grid>
    </layoutxml>
    <querytype>0</querytype>
    <fetchxml>
      <fetch version="1.0" mapping="logical">
        <entity name="ans_upload">
          <attribute name="ans_uploadid" />
          <attribute name="ans_filename" />
          <attribute name="createdon" />
          <order attribute="ans_filename" descending="false" />
          <filter type="and">
            <condition attribute="statecode" operator="eq" value="1" />
          </filter>
        </entity>
      </fetch>
    </fetchxml>
    <IntroducedVersion>1.0</IntroducedVersion>
    <LocalizedNames>
      <LocalizedName description="Inactive Uploads" languagecode="1033" />
    </LocalizedNames>
  </savedquery>
</savedqueries>