<?xml version="1.0" encoding="utf-8"?>
<savedqueries xmlns:xsi="http://www.w3.org/2001/XMLSchema-instance">
  <savedquery>
    <IsCustomizable>1</IsCustomizable>
    <CanBeDeleted>0</CanBeDeleted>
    <isquickfindquery>0</isquickfindquery>
    <isprivate>0</isprivate>
    <isdefault>1</isdefault>
    <savedqueryid>{e80dcfcd-9038-4fa1-9b69-4dcbdf2ab796}</savedqueryid>
    <layoutxml>
      <grid name="resultset" jump="ans_promptruleref" select="1" icon="1" preview="1">
        <row name="result" id="ans_promptruleid">
          <cell name="ans_rule" width="100" />
          <cell name="a_723a04f18d6d43bbb2765f08982bc658.ans_ruletext" width="300" />
        </row>
      </grid>
    </layoutxml>
    <querytype>0</querytype>
    <fetchxml>
      <fetch version="1.0" mapping="logical">
        <entity name="ans_promptrule">
          <attribute name="ans_promptruleid" />
          <filter type="and">
            <condition attribute="statecode" operator="eq" value="0" />
          </filter>
          <link-entity alias="a_723a04f18d6d43bbb2765f08982bc658" name="ans_rule" to="ans_rule" from="ans_ruleid" link-type="outer" visible="false">
            <attribute name="ans_ruletext" />
          </link-entity>
          <attribute name="ans_rule" />
        </entity>
      </fetch>
    </fetchxml>
    <IntroducedVersion>1.0</IntroducedVersion>
    <LocalizedNames>
      <LocalizedName description="Active Prompt Rules" languagecode="1033" />
    </LocalizedNames>
  </savedquery>
</savedqueries>